{"packages":{"friendlyit\/search":{"0.1.6":{"name":"friendlyit\/search","module":"friendlyit\/search","type":"pagekit-extension","title":"Search","description":"Add a configurable search form to your site.","license":"MIT","authors":[{"name":"Friendly-IT","email":"info@friendly-it.ru","homepage":"http:\/\/pagekit.friendly-it.ru\/"}],"extra":{"icon":"icon.svg","scripts":"scripts.php"},"archive":{"exclude":["node_modules","!\/app"]},"dist":{"type":"zip","url":"https:\/\/pagekit.com\/package\/friendlyit\/search\/0.1.6.zip","shasum":"b263c024ab17d7bd0f38bd5b3d748642f804448d"},"uid":189,"version":"0.1.6","version_normalized":"0.1.6.0"},"0.1.5":{"name":"friendlyit\/search","module":"friendlyit\/search","type":"pagekit-extension","title":"Search","description":"Add a configurable search form to your site.","license":"MIT","authors":[{"name":"Friendly-IT","email":"info@friendly-it.ru","homepage":"http:\/\/pagekit.friendly-it.ru\/"}],"extra":{"icon":"icon.svg","scripts":"scripts.php"},"archive":{"exclude":["node_modules","!\/app"]},"dist":{"type":"zip","url":"https:\/\/pagekit.com\/package\/friendlyit\/search\/0.1.5.zip","shasum":"bf00a54b96b163b75d632940be927fa940e0078b"},"uid":160,"version":"0.1.5","version_normalized":"0.1.5.0"},"0.1.3":{"name":"friendlyit\/search","module":"friendlyit\/search","type":"pagekit-extension","title":"Search","description":"Add a configurable search form to your site.","license":"MIT","authors":[{"name":"Friendly-IT","email":"info@friendly-it.ru","homepage":"http:\/\/pagekit.friendly-it.ru\/"}],"extra":{"icon":"icon.svg","scripts":"scripts.php"},"archive":{"exclude":["node_modules","!\/app"]},"dist":{"type":"zip","url":"https:\/\/pagekit.com\/package\/friendlyit\/search\/0.1.3.zip","shasum":"9abcb2f0e609dcf2af66781c9a1abe667fe4fc86"},"uid":153,"version":"0.1.3","version_normalized":"0.1.3.0"}}}}